nfis/__init__.py
nfis/funcs.py
nfis/ls_imager.py
nfis/mf_imager.py
nfis/simulator.py
nfis-0.1.5.dist-info/METADATA
nfis-0.1.5.dist-info/WHEEL
nfis-0.1.5.dist-info/RECORD
