Metadata-Version: 2.1
Name: nfis
Version: 0.1.5
Summary: Near field imager and simulator for radio interferometers
Author: satyapan
Author-email: satyapan.iiserm@gmail.com
Classifier: Programming Language :: Python :: 2
Classifier: Programming Language :: Python :: 2.7
Classifier: Programming Language :: Python :: 3
Classifier: Programming Language :: Python :: 3.4
Classifier: Programming Language :: Python :: 3.5
Classifier: Programming Language :: Python :: 3.6
Classifier: Programming Language :: Python :: 3.7
Classifier: Programming Language :: Python :: 3.8
Classifier: Programming Language :: Python :: 3.9
Classifier: Programming Language :: Python :: 3.10
Classifier: Programming Language :: Python :: 3.11
Classifier: Programming Language :: Python :: 3.12
Requires-Dist: astropy
Requires-Dist: imageio
Requires-Dist: lofarantpos
Requires-Dist: matplotlib
Requires-Dist: numexpr
Requires-Dist: numpy
Requires-Dist: python-casacore
Requires-Dist: scipy
Requires-Dist: tqdm
